alibabacloud_dataworks_public20240518/__init__.py
alibabacloud_dataworks_public20240518/client.py
alibabacloud_dataworks_public20240518/models/__init__.py
alibabacloud_dataworks_public20240518/models/_abolish_pipeline_run_request.py
alibabacloud_dataworks_public20240518/models/_abolish_pipeline_run_response.py
alibabacloud_dataworks_public20240518/models/_abolish_pipeline_run_response_body.py
alibabacloud_dataworks_public20240518/models/_add_entity_into_meta_collection_request.py
alibabacloud_dataworks_public20240518/models/_add_entity_into_meta_collection_response.py
alibabacloud_dataworks_public20240518/models/_add_entity_into_meta_collection_response_body.py
alibabacloud_dataworks_public20240518/models/_associate_project_to_resource_group_request.py
alibabacloud_dataworks_public20240518/models/_associate_project_to_resource_group_response.py
alibabacloud_dataworks_public20240518/models/_associate_project_to_resource_group_response_body.py
alibabacloud_dataworks_public20240518/models/_attach_data_quality_rules_to_evaluation_task_request.py
alibabacloud_dataworks_public20240518/models/_attach_data_quality_rules_to_evaluation_task_response.py
alibabacloud_dataworks_public20240518/models/_attach_data_quality_rules_to_evaluation_task_response_body.py
alibabacloud_dataworks_public20240518/models/_attach_data_quality_rules_to_evaluation_task_shrink_request.py
alibabacloud_dataworks_public20240518/models/_batch_update_tasks_request.py
alibabacloud_dataworks_public20240518/models/_batch_update_tasks_response.py
alibabacloud_dataworks_public20240518/models/_batch_update_tasks_response_body.py
alibabacloud_dataworks_public20240518/models/_batch_update_tasks_shrink_request.py
alibabacloud_dataworks_public20240518/models/_catalog.py
alibabacloud_dataworks_public20240518/models/_clone_data_source_request.py
alibabacloud_dataworks_public20240518/models/_clone_data_source_response.py
alibabacloud_dataworks_public20240518/models/_clone_data_source_response_body.py
alibabacloud_dataworks_public20240518-8.0.3.dist-info/LICENSE
alibabacloud_dataworks_public20240518-8.0.3.dist-info/METADATA
alibabacloud_dataworks_public20240518-8.0.3.dist-info/WHEEL
alibabacloud_dataworks_public20240518-8.0.3.dist-info/top_level.txt
alibabacloud_dataworks_public20240518-8.0.3.dist-info/RECORD
